pathme/__init__.py
pathme/__main__.py
pathme/cli.py
pathme/constants.py
pathme/mappings_parser.py
pathme/utils.py
pathme/kegg/__init__.py
pathme/kegg/convert_to_bel.py
pathme/kegg/kegg_xml_parser.py
pathme/kegg/utils.py
pathme/reactome/__init__.py
pathme/reactome/convert_to_bel.py
pathme/reactome/rdf_sparql.py
pathme/reactome/utils.py
pathme/wikipathways/__init__.py
pathme/wikipathways/convert_to_bel.py
pathme/wikipathways/json_rdf_parser.py
pathme/wikipathways/rdf_sparql.py
pathme/wikipathways/utils.py
pathme-0.0.11.dist-info/AUTHORS.rst
pathme-0.0.11.dist-info/LICENSE
pathme-0.0.11.dist-info/METADATA
pathme-0.0.11.dist-info/WHEEL
pathme-0.0.11.dist-info/entry_points.txt
pathme-0.0.11.dist-info/top_level.txt
pathme-0.0.11.dist-info/RECORD
