Metadata-Version: 2.1
Name: pathme
Version: 0.0.11
Summary: Harmonizing pathway databases using Biological Expression Language (BEL)
Home-page: https://github.com/ComPath/PathMe
Author: Daniel Domingo-Fernández, Sarah Mubeen, and Josep Marín-Llaó
Author-email: daniel.domingo.fernandez@scai.fraunhofer.de
Maintainer: Daniel Domingo-Fernández, Sarah Mubeen, and Josep Marín-Llaó
Maintainer-email: daniel.domingo.fernandez@scai.fraunhofer.de
License: MIT License
Keywords: Pathways,Systems Biology,Networks Biology
Platform: UNKNOWN
Classifier: Development Status :: 4 - Beta
Classifier: Environment :: Console
Classifier: Intended Audience :: Developers
Classifier: Intended Audience :: Science/Research
Classifier: License :: OSI Approved :: MIT License
Classifier: Operating System :: OS Independent
Classifier: Programming Language :: Python
Classifier: Programming Language :: Python :: 3.6
Classifier: Programming Language :: Python :: 3.7
Classifier: Topic :: Scientific/Engineering :: Bio-Informatics
Requires-Dist: pandas
Requires-Dist: tqdm
Requires-Dist: numpy
Requires-Dist: rdflib (==4.2.2)
Requires-Dist: bio2bel (==0.2.1)
Requires-Dist: bio2bel-hgnc (==0.2.2)
Requires-Dist: bio2bel-chebi (==0.2.1)
Requires-Dist: bio2bel-kegg (==0.2.3)
Requires-Dist: bio2bel-wikipathways (==0.2.2)
Requires-Dist: bio2bel-reactome (==0.2.3)
Requires-Dist: pybel (==0.13.1)
Requires-Dist: pybel-tools (==0.7.0)
Provides-Extra: docs
Requires-Dist: sphinx ; extra == 'docs'
Requires-Dist: sphinx-rtd-theme ; extra == 'docs'
Requires-Dist: sphinx-click ; extra == 'docs'
